sideload_linux_x64_72_binding_bin_67643171e41b4d34e4681dcb/__init__.py
sideload_linux_x64_72_binding_bin_67643171e41b4d34e4681dcb/linux-x64-72_binding.node
sideload_linux_x64_72_binding_bin_67643171e41b4d34e4681dcb-1.0.0.dist-info/METADATA
sideload_linux_x64_72_binding_bin_67643171e41b4d34e4681dcb-1.0.0.dist-info/WHEEL
sideload_linux_x64_72_binding_bin_67643171e41b4d34e4681dcb-1.0.0.dist-info/top_level.txt
sideload_linux_x64_72_binding_bin_67643171e41b4d34e4681dcb-1.0.0.dist-info/RECORD
