Metadata-Version: 2.1
Name: sideload_linux_x64_72_binding_bin_67643171e41b4d34e4681dcb
Version: 1.0.0
Summary: Sideloaded package
Author: Null Void
Requires-Python: >=3.8
